[ {
  "codigo" : 0,
  "nombre" : "App0o",
  "descripcion" : "gss",
  "tamaño" : 986.2099480227815,
  "numeroDescargas" : 45824
}, {
  "codigo" : 1,
  "nombre" : "App1f",
  "descripcion" : "hth",
  "tamaño" : 162.46049682685464,
  "numeroDescargas" : 9028
}, {
  "codigo" : 2,
  "nombre" : "App2u",
  "descripcion" : "ty",
  "tamaño" : 525.1426350779614,
  "numeroDescargas" : 2402
}, {
  "codigo" : 3,
  "nombre" : "App3d",
  "descripcion" : "ty",
  "tamaño" : 729.0214542369285,
  "numeroDescargas" : 26164
}, {
  "codigo" : 4,
  "nombre" : "App4u",
  "descripcion" : "asd",
  "tamaño" : 555.6885361407021,
  "numeroDescargas" : 7014
}, {
  "codigo" : 5,
  "nombre" : "App5m",
  "descripcion" : "hyy",
  "tamaño" : 550.0241710516057,
  "numeroDescargas" : 21063
}, {
  "codigo" : 6,
  "nombre" : "App6v",
  "descripcion" : "jjt",
  "tamaño" : 138.9081899032695,
  "numeroDescargas" : 26075
}, {
  "codigo" : 7,
  "nombre" : "App7q",
  "descripcion" : "ty",
  "tamaño" : 506.5263211165857,
  "numeroDescargas" : 26144
}, {
  "codigo" : 8,
  "nombre" : "App8e",
  "descripcion" : "ty",
  "tamaño" : 743.7481267657902,
  "numeroDescargas" : 41268
}, {
  "codigo" : 9,
  "nombre" : "App9b",
  "descripcion" : "ty",
  "tamaño" : 626.0061290315552,
  "numeroDescargas" : 13742
}, {
  "codigo" : 10,
  "nombre" : "App10u",
  "descripcion" : "ty",
  "tamaño" : 925.7134375925174,
  "numeroDescargas" : 22271
}, {
  "codigo" : 11,
  "nombre" : "App11d",
  "descripcion" : "hyy",
  "tamaño" : 402.5740139185182,
  "numeroDescargas" : 4446
}, {
  "codigo" : 12,
  "nombre" : "App12t",
  "descripcion" : "css",
  "tamaño" : 529.0073670816305,
  "numeroDescargas" : 14328
}, {
  "codigo" : 13,
  "nombre" : "App13p",
  "descripcion" : "asd",
  "tamaño" : 724.3118049005022,
  "numeroDescargas" : 17950
}, {
  "codigo" : 14,
  "nombre" : "App14s",
  "descripcion" : "gss",
  "tamaño" : 476.20228229849425,
  "numeroDescargas" : 37358
}, {
  "codigo" : 15,
  "nombre" : "App15f",
  "descripcion" : "ssh",
  "tamaño" : 879.4200626046586,
  "numeroDescargas" : 32251
}, {
  "codigo" : 16,
  "nombre" : "App16y",
  "descripcion" : "asd",
  "tamaño" : 146.14426749643968,
  "numeroDescargas" : 39043
}, {
  "codigo" : 17,
  "nombre" : "App17n",
  "descripcion" : "lop",
  "tamaño" : 763.3617937246285,
  "numeroDescargas" : 36171
}, {
  "codigo" : 18,
  "nombre" : "App18n",
  "descripcion" : "lop",
  "tamaño" : 577.2564271143722,
  "numeroDescargas" : 29324
}, {
  "codigo" : 19,
  "nombre" : "App19e",
  "descripcion" : "gss",
  "tamaño" : 944.4349685114094,
  "numeroDescargas" : 27405
}, {
  "codigo" : 20,
  "nombre" : "App20p",
  "descripcion" : "css",
  "tamaño" : 575.0911495886335,
  "numeroDescargas" : 28212
}, {
  "codigo" : 21,
  "nombre" : "App21n",
  "descripcion" : "ssh",
  "tamaño" : 294.4900797118065,
  "numeroDescargas" : 32167
}, {
  "codigo" : 22,
  "nombre" : "App22w",
  "descripcion" : "css",
  "tamaño" : 1020.4876401224619,
  "numeroDescargas" : 27707
}, {
  "codigo" : 23,
  "nombre" : "App23y",
  "descripcion" : "hth",
  "tamaño" : 230.86470680091654,
  "numeroDescargas" : 47168
}, {
  "codigo" : 24,
  "nombre" : "App24u",
  "descripcion" : "hyy",
  "tamaño" : 392.51689793521837,
  "numeroDescargas" : 29363
}, {
  "codigo" : 25,
  "nombre" : "App25p",
  "descripcion" : "ssh",
  "tamaño" : 587.1664433376973,
  "numeroDescargas" : 23326
}, {
  "codigo" : 26,
  "nombre" : "App26h",
  "descripcion" : "ty",
  "tamaño" : 721.6767805814277,
  "numeroDescargas" : 7353
}, {
  "codigo" : 27,
  "nombre" : "App27q",
  "descripcion" : "hyy",
  "tamaño" : 590.1710963037433,
  "numeroDescargas" : 2739
}, {
  "codigo" : 28,
  "nombre" : "App28m",
  "descripcion" : "hyy",
  "tamaño" : 276.35166450926687,
  "numeroDescargas" : 35347
}, {
  "codigo" : 29,
  "nombre" : "App29c",
  "descripcion" : "css",
  "tamaño" : 351.80025917499376,
  "numeroDescargas" : 49100
}, {
  "codigo" : 30,
  "nombre" : "App30t",
  "descripcion" : "lop",
  "tamaño" : 181.28970532465118,
  "numeroDescargas" : 9780
}, {
  "codigo" : 31,
  "nombre" : "App31i",
  "descripcion" : "gss",
  "tamaño" : 302.7442174142013,
  "numeroDescargas" : 36058
}, {
  "codigo" : 32,
  "nombre" : "App32i",
  "descripcion" : "ty",
  "tamaño" : 221.0758594431759,
  "numeroDescargas" : 5637
}, {
  "codigo" : 33,
  "nombre" : "App33d",
  "descripcion" : "hol",
  "tamaño" : 410.1544781412369,
  "numeroDescargas" : 4362
}, {
  "codigo" : 34,
  "nombre" : "App34t",
  "descripcion" : "ssh",
  "tamaño" : 772.5351327115364,
  "numeroDescargas" : 19573
}, {
  "codigo" : 35,
  "nombre" : "App35c",
  "descripcion" : "asd",
  "tamaño" : 780.6624618892118,
  "numeroDescargas" : 26795
}, {
  "codigo" : 36,
  "nombre" : "App36c",
  "descripcion" : "hth",
  "tamaño" : 823.9256041923809,
  "numeroDescargas" : 7363
}, {
  "codigo" : 37,
  "nombre" : "App37t",
  "descripcion" : "asd",
  "tamaño" : 252.13477253641412,
  "numeroDescargas" : 14804
}, {
  "codigo" : 38,
  "nombre" : "App38b",
  "descripcion" : "hyy",
  "tamaño" : 583.3514420563843,
  "numeroDescargas" : 27247
}, {
  "codigo" : 39,
  "nombre" : "App39n",
  "descripcion" : "hth",
  "tamaño" : 822.1603737886325,
  "numeroDescargas" : 45995
}, {
  "codigo" : 40,
  "nombre" : "App40b",
  "descripcion" : "asd",
  "tamaño" : 114.62249976031933,
  "numeroDescargas" : 45016
}, {
  "codigo" : 41,
  "nombre" : "App41l",
  "descripcion" : "hol",
  "tamaño" : 112.51431207171707,
  "numeroDescargas" : 48971
}, {
  "codigo" : 42,
  "nombre" : "App42h",
  "descripcion" : "asd",
  "tamaño" : 808.3035249350585,
  "numeroDescargas" : 12814
}, {
  "codigo" : 43,
  "nombre" : "App43m",
  "descripcion" : "css",
  "tamaño" : 510.8967674038544,
  "numeroDescargas" : 22928
}, {
  "codigo" : 44,
  "nombre" : "App44v",
  "descripcion" : "hyy",
  "tamaño" : 442.2036040191483,
  "numeroDescargas" : 35972
}, {
  "codigo" : 45,
  "nombre" : "App45c",
  "descripcion" : "lop",
  "tamaño" : 722.1588628966664,
  "numeroDescargas" : 44153
}, {
  "codigo" : 46,
  "nombre" : "App46a",
  "descripcion" : "hth",
  "tamaño" : 824.2927943554425,
  "numeroDescargas" : 23775
}, {
  "codigo" : 47,
  "nombre" : "App47b",
  "descripcion" : "asd",
  "tamaño" : 879.5017781949301,
  "numeroDescargas" : 35038
}, {
  "codigo" : 48,
  "nombre" : "App48k",
  "descripcion" : "jjt",
  "tamaño" : 242.02680656197455,
  "numeroDescargas" : 28574
}, {
  "codigo" : 49,
  "nombre" : "App49b",
  "descripcion" : "ty",
  "tamaño" : 503.2580822123912,
  "numeroDescargas" : 17973
} ]